{
    "question": {
        "owner": {
            "profile_image": "https://www.gravatar.com/avatar/282aeb00d8f29253e694199b462906bb?s=256&d=identicon&r=PG&f=y&so-version=2",
            "account_id": 3343863,
            "user_type": "registered",
            "user_id": 2809437,
            "link": "https://stackoverflow.com/users/2809437/user2809437",
            "reputation": 492,
            "display_name": "user2809437",
            "accept_rate": 46
        },
        "content_license": "CC BY-SA 3.0",
        "link": "https://stackoverflow.com/questions/20012703/file-i-o-java-absolute-vs-relative-file-name",
        "last_activity_date": 1384561354,
        "creation_date": 1384559582,
        "answer_count": 3,
        "title": "file I/O java absolute vs. relative file name",
        "body": "<p>For File I/O. We were told to use relative file name vs. absolute file name. So my question is Why is it better to use the relative file name rather than the absolute?<\/p>\n",
        "question_id": 20012703,
        "tags": ["java"],
        "score": 0,
        "is_answered": true,
        "view_count": 376
    },
    "question_comments": [],
    "answers": [
        {
            "owner": {
                "profile_image": "https://www.gravatar.com/avatar/3e8334fa0af5438d958afeb566440cca?s=256&d=identicon&r=PG",
                "account_id": 3034809,
                "user_type": "registered",
                "user_id": 2573153,
                "link": "https://stackoverflow.com/users/2573153/user2573153",
                "reputation": 252,
                "display_name": "user2573153",
                "accept_rate": 78
            },
            "content_license": "CC BY-SA 3.0",
            "score": 1,
            "is_accepted": false,
            "last_activity_date": 1384559711,
            "creation_date": 1384559711,
            "body": "<p>The absolute filename is platform dependent whereas the relative one just points from the folder you're in.<\/p>\n",
            "answer_id": 20012722,
            "question_id": 20012703
        },
        {
            "owner": {
                "profile_image": "https://www.gravatar.com/avatar/147c5a9cc1feec049c50da791ac7d144?s=256&d=identicon&r=PG",
                "account_id": 47283,
                "user_type": "registered",
                "user_id": 139985,
                "link": "https://stackoverflow.com/users/139985/stephen-c",
                "reputation": 723474,
                "display_name": "Stephen C",
                "accept_rate": 69
            },
            "content_license": "CC BY-SA 3.0",
            "score": 1,
            "is_accepted": false,
            "last_activity_date": 1384561354,
            "creation_date": 1384560013,
            "body": "<blockquote>\n  <p>Why is it better to use the relative file name rather than the absolute?<\/p>\n<\/blockquote>\n\n<p>It depends on what you are actually doing.  In fact, for some purposes absolute paths are better than relative paths.<\/p>\n\n<p>The main advantage of an absolute path is that it always means the same thing.<\/p>\n\n<p>The main disadvantage of an absolute path is that if you move a file (or tree) you change its absolute path.  If you previous saved the location of some file as an absolute path, you now have to change it.<\/p>\n\n<p>The advantages of relative paths are<\/p>\n\n<ul>\n<li>that they are shorter, <\/li>\n<li>they are generally more user friendly, and<\/li>\n<li>they can<sup>1<\/sup> make it easier to deal with collections of files that have moved.<\/li>\n<\/ul>\n\n<p>But the disadvantage is that a relative path (at least in Java with a <code>File<\/code> object) is <em>resolved<\/em> relative to the JVM's <em>current directory<\/em>.  In a lot of situations there is uncertainty (in the mind of the user and/or developer) over what it actually is.  And if it is not what you expect, a relative path with resolve incorrectly.<\/p>\n\n<hr>\n\n<p><sup>1 - The caveat is that you are actually relying on the JVM being <em>launched<\/em> with the appropriate <em>current directory<\/em>.  Once the JVM has launched, it cannot change its current directory.  Or at least, you can't do it in pure Java ... AFAIK.<\/sup><\/p>\n",
            "answer_id": 20012775,
            "question_id": 20012703,
            "last_edit_date": 1384561354
        },
        {
            "owner": {
                "profile_image": "https://i.sstatic.net/cjrhn.png?s=256",
                "account_id": 2766699,
                "user_type": "registered",
                "user_id": 2382246,
                "link": "https://stackoverflow.com/users/2382246/blalasaadri",
                "reputation": 6216,
                "display_name": "blalasaadri",
                "accept_rate": 100
            },
            "content_license": "CC BY-SA 3.0",
            "score": 0,
            "is_accepted": false,
            "last_activity_date": 1384560120,
            "creation_date": 1384560120,
            "body": "<p>If you move your project to another system there are two kinds of problems you could run into with absolute paths:<\/p>\n\n<ol>\n<li>The resources may reside at different places in the file system<\/li>\n<li>You may be using a different <em>kind<\/em> of operating system (e.g. Windows vs. Linux/Unix). Those systems use totally different kinds of path descriptors.<\/li>\n<\/ol>\n",
            "answer_id": 20012789,
            "question_id": 20012703
        }
    ],
    "answer_comments": {}
}