{
    "question": {
        "owner": {
            "profile_image": "https://www.gravatar.com/avatar/a88910d48d0eafd9aa4e5a92ae6004df?s=256&d=identicon&r=PG",
            "account_id": 2136016,
            "user_type": "registered",
            "user_id": 1895798,
            "link": "https://stackoverflow.com/users/1895798/user1895798",
            "reputation": 11,
            "display_name": "user1895798"
        },
        "content_license": "CC BY-SA 3.0",
        "link": "https://stackoverflow.com/questions/13827754/strange-error-launch-java-eclypse",
        "last_activity_date": 1355257112,
        "creation_date": 1355256798,
        "answer_count": 3,
        "title": "Strange Error launch Java (Eclypse)",
        "body": "<p>I read the discussions about this problem, but I couldn't find a solution for it!<\/p>\n\n<p>I wrote a very easy program, but as I launch it, this error appears:<\/p>\n\n<pre><code>           &lt;&lt; Selection does not contain a main type &gt;&gt;\n<\/code><\/pre>\n\n<p>Thank you very much in advance to whom will help me. I am new of Java:/<\/p>\n\n<hr>\n\n<pre><code>public class Implementation{\n\n  public static void Main(String args[]){\n\n    Operations_numbers operations;\n    operations = new Operations_numbers();\n\n    int subtraction = operations.subtraction(10,2);\n    String result_Comparison = new String();\n    result_Comparison = operations.comparison(8,3);\n\n    System.out.println(result_Comparison); \n    System.out.println(subtraction); \n\n  }\n\n}\n---------------\npublic class Operations_numbers{\n\n  public int subtraction (int x, int y){\n    int subtraction;\n    subtraction=x-y; \n    return subtraction;\n  }\n\n  public String comparison (int x, int y){    \n    if(x&gt;y){    \n      String result=\"the number\" + x + \"is bigger than the number\" + y;\n      return result;\n    }    \n    else{  \n      String result=\"the number\" + y + \"is bigger than the numbero\" + x;\n      return result;\n    }\n  }\n\n}\n<\/code><\/pre>\n",
        "question_id": 13827754,
        "tags": [
            "java",
            "launch"
        ],
        "score": 1,
        "is_answered": true,
        "view_count": 63
    },
    "question_comments": [],
    "answers": [
        {
            "owner": {
                "profile_image": "https://www.gravatar.com/avatar/773332bfee8105f9738c50c0f89c9242?s=256&d=identicon&r=PG",
                "account_id": 287206,
                "user_type": "registered",
                "user_id": 586880,
                "link": "https://stackoverflow.com/users/586880/diego-basch",
                "reputation": 13089,
                "display_name": "Diego Basch"
            },
            "content_license": "CC BY-SA 3.0",
            "score": 2,
            "is_accepted": false,
            "last_activity_date": 1355257073,
            "creation_date": 1355257073,
            "body": "<p><code>main<\/code> should be lowercase. The proper signature is<\/p>\n\n<pre><code>public static void main(String args[])\n<\/code><\/pre>\n",
            "answer_id": 13827824,
            "question_id": 13827754
        },
        {
            "owner": {
                "profile_image": "https://www.gravatar.com/avatar/53f72057e19fe7bfd0eaff8ab7897ccc?s=256&d=identicon&r=PG",
                "account_id": 2135882,
                "user_type": "registered",
                "user_id": 1895701,
                "link": "https://stackoverflow.com/users/1895701/boni",
                "reputation": 1,
                "display_name": "boni"
            },
            "content_license": "CC BY-SA 3.0",
            "score": 0,
            "is_accepted": false,
            "last_activity_date": 1355257074,
            "creation_date": 1355257074,
            "body": "<p>Function names are case sensitive. As the error message suggests it can't find the main function. However you defined a Main function. Try it with lowercase main. :)<\/p>\n",
            "answer_id": 13827825,
            "question_id": 13827754
        },
        {
            "owner": {
                "profile_image": "https://i.sstatic.net/0k2MyaTC.jpg?s=256",
                "account_id": 2072309,
                "user_type": "registered",
                "user_id": 1846480,
                "link": "https://stackoverflow.com/users/1846480/marcio-junior",
                "reputation": 19118,
                "display_name": "Marcio Junior"
            },
            "content_license": "CC BY-SA 3.0",
            "score": 0,
            "is_accepted": false,
            "last_activity_date": 1355257109,
            "creation_date": 1355257109,
            "body": "<p>You have to change<\/p>\n\n<pre><code>public static void Main(String args[]) {/* code */}\n<\/code><\/pre>\n\n<p>to<\/p>\n\n<pre><code>public static void main(String args[]) { /* code */ }\n<\/code><\/pre>\n\n<p>Because java is case sensitive and expect a method called main, in downcase, as entry point.<\/p>\n",
            "answer_id": 13827835,
            "question_id": 13827754
        }
    ],
    "answer_comments": {
        "13827825": [{
            "owner": {
                "profile_image": "https://www.gravatar.com/avatar/a88910d48d0eafd9aa4e5a92ae6004df?s=256&d=identicon&r=PG",
                "account_id": 2136016,
                "user_type": "registered",
                "user_id": 1895798,
                "link": "https://stackoverflow.com/users/1895798/user1895798",
                "reputation": 11,
                "display_name": "user1895798"
            },
            "content_license": "CC BY-SA 3.0",
            "score": 0,
            "post_id": 13827825,
            "edited": false,
            "creation_date": 1355259200,
            "comment_id": 19030489
        }],
        "13827824": [{
            "owner": {
                "profile_image": "https://www.gravatar.com/avatar/a88910d48d0eafd9aa4e5a92ae6004df?s=256&d=identicon&r=PG",
                "account_id": 2136016,
                "user_type": "registered",
                "user_id": 1895798,
                "link": "https://stackoverflow.com/users/1895798/user1895798",
                "reputation": 11,
                "display_name": "user1895798"
            },
            "content_license": "CC BY-SA 3.0",
            "score": 0,
            "post_id": 13827824,
            "edited": false,
            "creation_date": 1355258954,
            "comment_id": 19030374
        }],
        "13827835": [{
            "owner": {
                "profile_image": "https://www.gravatar.com/avatar/a88910d48d0eafd9aa4e5a92ae6004df?s=256&d=identicon&r=PG",
                "account_id": 2136016,
                "user_type": "registered",
                "user_id": 1895798,
                "link": "https://stackoverflow.com/users/1895798/user1895798",
                "reputation": 11,
                "display_name": "user1895798"
            },
            "content_license": "CC BY-SA 3.0",
            "score": 0,
            "post_id": 13827835,
            "edited": false,
            "creation_date": 1355259134,
            "comment_id": 19030456
        }]
    }
}