{
    "question": {
        "owner": {
            "profile_image": "https://www.gravatar.com/avatar/ba559937a353f2e8ec198c172ee20b0a?s=256&d=identicon&r=PG",
            "account_id": 1545748,
            "user_type": "registered",
            "user_id": 1439333,
            "link": "https://stackoverflow.com/users/1439333/vishnudev-k",
            "reputation": 2944,
            "display_name": "Vishnudev K",
            "accept_rate": 70
        },
        "content_license": "CC BY-SA 3.0",
        "link": "https://stackoverflow.com/questions/19338927/how-can-i-access-the-files-from-admins-google-drive-in-a-google-appengine-app",
        "last_activity_date": 1381612051,
        "creation_date": 1381610027,
        "answer_count": 1,
        "title": "How can I access the files from admin&#39;s google drive in a google appengine app",
        "body": "<p>I wanted to access the files stored by the admin in google drive in my app engine app.<\/p>\n\n<p>Currently I am able to access the contents in \"Application Data\" which is hidden and difficult to manage.<\/p>\n\n<p>I wanted to access the files stored in admin's google drive . (which is visible and can be managed through UI <a href=\"https://drive.google.com/#my-drive\" rel=\"nofollow\">https://drive.google.com/#my-drive<\/a>).<\/p>\n\n<p>(In Java)<\/p>\n",
        "question_id": 19338927,
        "tags": [
            "java",
            "google-app-engine",
            "google-drive-api",
            "google-data-api"
        ],
        "score": 1,
        "is_answered": false,
        "view_count": 170
    },
    "question_comments": [],
    "answers": [{
        "owner": {
            "profile_image": "https://i.sstatic.net/NEbb2.jpg?s=256",
            "account_id": 2549951,
            "user_type": "registered",
            "user_id": 2213940,
            "link": "https://stackoverflow.com/users/2213940/zig-mandel",
            "reputation": 19928,
            "display_name": "Zig Mandel"
        },
        "content_license": "CC BY-SA 3.0",
        "score": 0,
        "is_accepted": false,
        "last_activity_date": 1381612051,
        "creation_date": 1381612051,
        "body": "<p>Either run the oauth flow to get the admin refresh token, or share the admin folder you want with the special  user that appengine has.<\/p>\n",
        "answer_id": 19339216,
        "question_id": 19338927
    }],
    "answer_comments": {"19339216": [
        {
            "owner": {
                "profile_image": "https://www.gravatar.com/avatar/23634e7a38e353cca12bb72a4205615b?s=256&d=identicon&r=PG",
                "account_id": 981041,
                "user_type": "registered",
                "user_id": 1000753,
                "link": "https://stackoverflow.com/users/1000753/pinoyyid",
                "reputation": 22436,
                "display_name": "pinoyyid",
                "accept_rate": 65
            },
            "content_license": "CC BY-SA 3.0",
            "score": 1,
            "post_id": 19339216,
            "edited": false,
            "creation_date": 1381676691,
            "comment_id": 28662968
        },
        {
            "owner": {
                "profile_image": "https://www.gravatar.com/avatar/ba559937a353f2e8ec198c172ee20b0a?s=256&d=identicon&r=PG",
                "account_id": 1545748,
                "user_type": "registered",
                "user_id": 1439333,
                "link": "https://stackoverflow.com/users/1439333/vishnudev-k",
                "reputation": 2944,
                "display_name": "Vishnudev K",
                "accept_rate": 70
            },
            "content_license": "CC BY-SA 3.0",
            "score": 0,
            "post_id": 19339216,
            "edited": false,
            "creation_date": 1381646735,
            "comment_id": 28655995
        }
    ]}
}