{
    "question": {
        "owner": {
            "profile_image": "https://www.gravatar.com/avatar/038e5853a4aaec6cc9ea7ec7a9ace63d?s=256&d=identicon&r=PG&f=y&so-version=2",
            "account_id": 12461045,
            "user_type": "registered",
            "user_id": 9072667,
            "link": "https://stackoverflow.com/users/9072667/ricky",
            "reputation": 109,
            "display_name": "Ricky"
        },
        "content_license": "CC BY-SA 4.0",
        "link": "https://stackoverflow.com/questions/58447866/how-to-call-an-abstract-method-overridden-in-subclasses-from-the-superclass",
        "last_activity_date": 1571392074,
        "creation_date": 1571390722,
        "answer_count": 2,
        "title": "How to call an abstract method (overridden in subclasses) from the superclass?",
        "body": "<p>I have an abstract method in an abstract class, Student. \nThe Subclass, JUPASStudent overrides it. \nNow I am trying to sort the ArrayList of type Student. It requires to call that abstract method but I am unable to do so. <\/p>\n\n<p>I am writing here my partial code.<\/p>\n\n<p>Superclass:<\/p>\n\n<pre><code>abstract class Student {\n    protected String name;\n\n    public Student (String name) {\n        this.name = name;\n    }\n\n    public String getName() {\n        return name;\n    }\n    abstract double getResult(); //abstract method \n\n}\n\n<\/code><\/pre>\n\n<p>Subclass: <\/p>\n\n<pre><code>public class JUPASStudent extends Student {\n    private double dseResult;\n\n    public JUPASStudent(String n, double d) {\n        super (n);\n        this.dseResult = d;\n    }\n\n    public double getResult() {\n        return dseResult;   //abstract method is overridden here\n    }\n    public String getName() {\n        return super.name;\n    }\n    public void setResult(double dseResult) { \n        this.dseResult = dseResult;\n    }\n    public void setName(String name) {\n        super.name = name;\n    }\n}\n\n<\/code><\/pre>\n\n<p>Now I am writing a Sort function to make an ArrayList (Student class)<\/p>\n\n<pre><code>public ArrayList &lt;Student&gt; sort(ArrayList&lt;Student&gt; sList){\n        sList.sort(Comparator.comparingInt(Student::getResult));\n        return sList;\n    }\n<\/code><\/pre>\n\n<p>Input: <\/p>\n\n<pre><code>A 9\nB 5\nC 8\n<\/code><\/pre>\n\n<p>Expected Output:<\/p>\n\n<pre><code>B 5\nC 8\nA 9\n<\/code><\/pre>\n\n<p>Error<\/p>\n\n<pre><code>-The method comparingInt(ToIntFunction&lt;? super T&gt;) in the type Comparator is not applicable for the arguments (Student::getResult) \n\n-The type Student does not define getResult(T) that is applicable here\n<\/code><\/pre>\n",
        "question_id": 58447866,
        "tags": [
            "java",
            "sorting",
            "methods",
            "polymorphism",
            "superclass"
        ],
        "score": 0,
        "is_answered": false,
        "view_count": 136,
        "last_edit_date": 1571391349
    },
    "question_comments": [
        {
            "owner": {
                "profile_image": "https://www.gravatar.com/avatar/9c48b77ff7a5c251b485a14445980268?s=256&d=identicon&r=PG&f=y&so-version=2",
                "account_id": 5042214,
                "user_type": "registered",
                "user_id": 4049220,
                "link": "https://stackoverflow.com/users/4049220/k-d",
                "reputation": 417,
                "display_name": "K.D"
            },
            "content_license": "CC BY-SA 4.0",
            "score": 0,
            "post_id": 58447866,
            "edited": false,
            "creation_date": 1571392297,
            "comment_id": 103234592
        },
        {
            "owner": {
                "profile_image": "https://www.gravatar.com/avatar/038e5853a4aaec6cc9ea7ec7a9ace63d?s=256&d=identicon&r=PG&f=y&so-version=2",
                "account_id": 12461045,
                "user_type": "registered",
                "user_id": 9072667,
                "link": "https://stackoverflow.com/users/9072667/ricky",
                "reputation": 109,
                "display_name": "Ricky"
            },
            "content_license": "CC BY-SA 4.0",
            "score": 0,
            "post_id": 58447866,
            "edited": false,
            "creation_date": 1571392045,
            "comment_id": 103234464
        },
        {
            "owner": {
                "profile_image": "https://www.gravatar.com/avatar/8fbe63f77ce3f9656c62b27db4d8583b?s=256&d=identicon&r=PG",
                "account_id": 785560,
                "user_type": "registered",
                "user_id": 845414,
                "link": "https://stackoverflow.com/users/845414/johannes-kuhn",
                "reputation": 15259,
                "display_name": "Johannes Kuhn"
            },
            "content_license": "CC BY-SA 4.0",
            "score": 0,
            "post_id": 58447866,
            "edited": false,
            "creation_date": 1571391758,
            "comment_id": 103234327
        },
        {
            "owner": {
                "profile_image": "https://www.gravatar.com/avatar/038e5853a4aaec6cc9ea7ec7a9ace63d?s=256&d=identicon&r=PG&f=y&so-version=2",
                "account_id": 12461045,
                "user_type": "registered",
                "user_id": 9072667,
                "link": "https://stackoverflow.com/users/9072667/ricky",
                "reputation": 109,
                "display_name": "Ricky"
            },
            "content_license": "CC BY-SA 4.0",
            "score": 0,
            "post_id": 58447866,
            "reply_to_user": {
                "profile_image": "https://i.sstatic.net/0HpYR.png?s=256",
                "account_id": 4728704,
                "user_type": "registered",
                "user_id": 3824919,
                "link": "https://stackoverflow.com/users/3824919/tom",
                "reputation": 17727,
                "display_name": "Tom"
            },
            "edited": false,
            "creation_date": 1571391389,
            "comment_id": 103234135
        },
        {
            "owner": {
                "profile_image": "https://www.gravatar.com/avatar/038e5853a4aaec6cc9ea7ec7a9ace63d?s=256&d=identicon&r=PG&f=y&so-version=2",
                "account_id": 12461045,
                "user_type": "registered",
                "user_id": 9072667,
                "link": "https://stackoverflow.com/users/9072667/ricky",
                "reputation": 109,
                "display_name": "Ricky"
            },
            "content_license": "CC BY-SA 4.0",
            "score": 0,
            "post_id": 58447866,
            "reply_to_user": {
                "profile_image": "https://www.gravatar.com/avatar/9c48b77ff7a5c251b485a14445980268?s=256&d=identicon&r=PG&f=y&so-version=2",
                "account_id": 5042214,
                "user_type": "registered",
                "user_id": 4049220,
                "link": "https://stackoverflow.com/users/4049220/k-d",
                "reputation": 417,
                "display_name": "K.D"
            },
            "edited": false,
            "creation_date": 1571391259,
            "comment_id": 103234061
        },
        {
            "owner": {
                "profile_image": "https://i.sstatic.net/0HpYR.png?s=256",
                "account_id": 4728704,
                "user_type": "registered",
                "user_id": 3824919,
                "link": "https://stackoverflow.com/users/3824919/tom",
                "reputation": 17727,
                "display_name": "Tom"
            },
            "content_license": "CC BY-SA 4.0",
            "score": 0,
            "post_id": 58447866,
            "edited": false,
            "creation_date": 1571391206,
            "comment_id": 103234036
        },
        {
            "owner": {
                "profile_image": "https://www.gravatar.com/avatar/a2aa2525743dbdf65634cc11fae3b6ed?s=256&d=identicon&r=PG",
                "account_id": 2450346,
                "user_type": "registered",
                "user_id": 2136795,
                "link": "https://stackoverflow.com/users/2136795/gyro-gearless",
                "reputation": 5287,
                "display_name": "Gyro Gearless"
            },
            "content_license": "CC BY-SA 4.0",
            "score": 0,
            "post_id": 58447866,
            "edited": false,
            "creation_date": 1571391103,
            "comment_id": 103233969
        },
        {
            "owner": {
                "profile_image": "https://www.gravatar.com/avatar/9c48b77ff7a5c251b485a14445980268?s=256&d=identicon&r=PG&f=y&so-version=2",
                "account_id": 5042214,
                "user_type": "registered",
                "user_id": 4049220,
                "link": "https://stackoverflow.com/users/4049220/k-d",
                "reputation": 417,
                "display_name": "K.D"
            },
            "content_license": "CC BY-SA 4.0",
            "score": 0,
            "post_id": 58447866,
            "edited": false,
            "creation_date": 1571390835,
            "comment_id": 103233808
        }
    ],
    "answers": [
        {
            "owner": {
                "profile_image": "https://i.sstatic.net/ZXmea.jpg?s=256",
                "account_id": 8825915,
                "user_type": "registered",
                "user_id": 6594174,
                "link": "https://stackoverflow.com/users/6594174/leonardo-rey",
                "reputation": 737,
                "display_name": "leonardo rey"
            },
            "content_license": "CC BY-SA 4.0",
            "score": 0,
            "is_accepted": false,
            "last_activity_date": 1571390864,
            "creation_date": 1571390864,
            "body": "<p>If you have override the method in the subclass, it'll use the implementation of the subclass, so don't worry about calling it explicit, at least in your case<\/p>\n",
            "answer_id": 58447915,
            "question_id": 58447866
        },
        {
            "owner": {
                "profile_image": "https://www.gravatar.com/avatar/99a15220753626215c0ecf8072275bbb?s=256&d=identicon&r=PG&f=y&so-version=2",
                "account_id": 16669162,
                "user_type": "registered",
                "user_id": 12047085,
                "link": "https://stackoverflow.com/users/12047085/user12047085",
                "reputation": 162,
                "display_name": "user12047085"
            },
            "content_license": "CC BY-SA 4.0",
            "score": 0,
            "is_accepted": false,
            "last_activity_date": 1571392052,
            "creation_date": 1571392052,
            "body": "<p>getResult() is returning double, try returning Int and i think it would work.\nedit:\nor use comparingDouble() method<\/p>\n",
            "answer_id": 58448236,
            "question_id": 58447866
        }
    ],
    "answer_comments": {"58447915": [
        {
            "owner": {
                "profile_image": "https://i.sstatic.net/qGscz.jpg?s=256",
                "account_id": 3084067,
                "user_type": "registered",
                "user_id": 2611620,
                "link": "https://stackoverflow.com/users/2611620/kshitij-bajracharya",
                "reputation": 851,
                "display_name": "Kshitij Bajracharya",
                "accept_rate": 0
            },
            "content_license": "CC BY-SA 4.0",
            "score": 0,
            "post_id": 58447915,
            "reply_to_user": {
                "profile_image": "https://www.gravatar.com/avatar/038e5853a4aaec6cc9ea7ec7a9ace63d?s=256&d=identicon&r=PG&f=y&so-version=2",
                "account_id": 12461045,
                "user_type": "registered",
                "user_id": 9072667,
                "link": "https://stackoverflow.com/users/9072667/ricky",
                "reputation": 109,
                "display_name": "Ricky"
            },
            "edited": false,
            "creation_date": 1571393857,
            "comment_id": 103235392
        },
        {
            "owner": {
                "profile_image": "https://www.gravatar.com/avatar/038e5853a4aaec6cc9ea7ec7a9ace63d?s=256&d=identicon&r=PG&f=y&so-version=2",
                "account_id": 12461045,
                "user_type": "registered",
                "user_id": 9072667,
                "link": "https://stackoverflow.com/users/9072667/ricky",
                "reputation": 109,
                "display_name": "Ricky"
            },
            "content_license": "CC BY-SA 4.0",
            "score": 0,
            "post_id": 58447915,
            "edited": false,
            "creation_date": 1571391655,
            "comment_id": 103234275
        },
        {
            "owner": {
                "profile_image": "https://i.sstatic.net/ZXmea.jpg?s=256",
                "account_id": 8825915,
                "user_type": "registered",
                "user_id": 6594174,
                "link": "https://stackoverflow.com/users/6594174/leonardo-rey",
                "reputation": 737,
                "display_name": "leonardo rey"
            },
            "content_license": "CC BY-SA 4.0",
            "score": 1,
            "post_id": 58447915,
            "reply_to_user": {
                "profile_image": "https://www.gravatar.com/avatar/038e5853a4aaec6cc9ea7ec7a9ace63d?s=256&d=identicon&r=PG&f=y&so-version=2",
                "account_id": 12461045,
                "user_type": "registered",
                "user_id": 9072667,
                "link": "https://stackoverflow.com/users/9072667/ricky",
                "reputation": 109,
                "display_name": "Ricky"
            },
            "edited": false,
            "creation_date": 1571391182,
            "comment_id": 103234015
        },
        {
            "owner": {
                "profile_image": "https://www.gravatar.com/avatar/038e5853a4aaec6cc9ea7ec7a9ace63d?s=256&d=identicon&r=PG&f=y&so-version=2",
                "account_id": 12461045,
                "user_type": "registered",
                "user_id": 9072667,
                "link": "https://stackoverflow.com/users/9072667/ricky",
                "reputation": 109,
                "display_name": "Ricky"
            },
            "content_license": "CC BY-SA 4.0",
            "score": 0,
            "post_id": 58447915,
            "edited": false,
            "creation_date": 1571391134,
            "comment_id": 103233992
        },
        {
            "owner": {
                "profile_image": "https://www.gravatar.com/avatar/038e5853a4aaec6cc9ea7ec7a9ace63d?s=256&d=identicon&r=PG&f=y&so-version=2",
                "account_id": 12461045,
                "user_type": "registered",
                "user_id": 9072667,
                "link": "https://stackoverflow.com/users/9072667/ricky",
                "reputation": 109,
                "display_name": "Ricky"
            },
            "content_license": "CC BY-SA 4.0",
            "score": 0,
            "post_id": 58447915,
            "edited": false,
            "creation_date": 1571391038,
            "comment_id": 103233932
        }
    ]}
}