{
    "question": {
        "owner": {
            "profile_image": "https://www.gravatar.com/avatar/8a34f7c38326993309709d682cea2d64?s=256&d=identicon&r=PG&f=y&so-version=2",
            "account_id": 3218561,
            "user_type": "registered",
            "user_id": 2716525,
            "link": "https://stackoverflow.com/users/2716525/edu-shin",
            "reputation": 51,
            "display_name": "edu_shin"
        },
        "content_license": "CC BY-SA 3.0",
        "link": "https://stackoverflow.com/questions/18478428/draw-on-java-console-two-squares-one-inside-of-the-other",
        "last_activity_date": 1377661373,
        "creation_date": 1377656714,
        "answer_count": 1,
        "title": "Draw on Java console two squares (one inside of the other)",
        "body": "<p>basically I need to input two numbers and they will be the side size of two squares (drawn one inside of the other, being the inside square positioned in the middle of the biggest square). <\/p>\n\n<p>I really have no idea how to do this, and the only thing that I was able to come up with was inputing a value and having one drawn square:<\/p>\n\n<pre><code>package teste;\n\nimport java.util.Scanner;\n\npublic class Main {\n\nprivate static Scanner sc;\n\npublic static void main(String a[])\n{\n        int size=0;\n\n        System.out.print(\"Enter size: \");\n        sc = new Scanner(System.in);\n        size = sc.nextInt();\n\n        for(int i=1; i &lt;= size; i++){\n\n        for(int j=1; j &lt;= size; j++){\n\n            if(i==1 || i==size || j==1 || j==size)\n            System.out.print(\"*\");\n            else\n            System.out.print(\" \");\n                        }\n\n        System.out.println();\n                        }\n}       \n  }\n<\/code><\/pre>\n\n<p>I know it is not much, but my java skills are limited. Can you guys show a way to do it? I have no idea how to draw the square inside.<\/p>\n\n<p>Thanks in advance.<\/p>\n",
        "question_id": 18478428,
        "tags": [
            "java",
            "console",
            "drawing"
        ],
        "score": 1,
        "is_answered": false,
        "view_count": 1578,
        "last_edit_date": 1377657175
    },
    "question_comments": [
        {
            "owner": {
                "profile_image": "https://www.gravatar.com/avatar/8a34f7c38326993309709d682cea2d64?s=256&d=identicon&r=PG&f=y&so-version=2",
                "account_id": 3218561,
                "user_type": "registered",
                "user_id": 2716525,
                "link": "https://stackoverflow.com/users/2716525/edu-shin",
                "reputation": 51,
                "display_name": "edu_shin"
            },
            "content_license": "CC BY-SA 3.0",
            "score": 0,
            "post_id": 18478428,
            "reply_to_user": {
                "profile_image": "https://i.sstatic.net/Yk9I5.jpg?s=256",
                "account_id": 2882201,
                "user_type": "registered",
                "user_id": 2472820,
                "link": "https://stackoverflow.com/users/2472820/kon",
                "reputation": 10839,
                "display_name": "Kon",
                "accept_rate": 86
            },
            "edited": false,
            "creation_date": 1377658229,
            "comment_id": 27162251
        },
        {
            "owner": {
                "profile_image": "https://i.sstatic.net/Yk9I5.jpg?s=256",
                "account_id": 2882201,
                "user_type": "registered",
                "user_id": 2472820,
                "link": "https://stackoverflow.com/users/2472820/kon",
                "reputation": 10839,
                "display_name": "Kon",
                "accept_rate": 86
            },
            "content_license": "CC BY-SA 3.0",
            "score": 0,
            "post_id": 18478428,
            "edited": false,
            "creation_date": 1377657996,
            "comment_id": 27162193
        }
    ],
    "answers": [{
        "owner": {
            "profile_image": "https://i.sstatic.net/Me69G.jpg?s=256",
            "account_id": 2356565,
            "user_type": "registered",
            "user_id": 2064242,
            "link": "https://stackoverflow.com/users/2064242/alexander-zaykov",
            "reputation": 181,
            "display_name": "Alexander Zaykov"
        },
        "content_license": "CC BY-SA 3.0",
        "score": 0,
        "is_accepted": false,
        "last_activity_date": 1377661373,
        "creation_date": 1377661373,
        "body": "<p>The simplest way i see is just make a buffer where you will fill the characters you want to draw in console<\/p>\n\n<pre><code>    // init buffer\n    char buffer[][] = new char[size][];\n    for (int i = 0; i &lt; size; i ++) {\n        buffer[i] = new char[size];\n    }\n\n    // borders of first square\n    final int sq1Start = 0;\n    final int sq1End = size-1;\n\n    // draw outer square\n    for(int i = sq1Start; i &lt;= sq1End; i ++){\n        for (int j = sq1Start; j &lt;= sq1End; j ++) {\n            if (i == sq1Start || i == sq1End || j == sq1Start || j == sq1End) {\n                buffer[i][j] = '*';\n            }\n        }\n    }\n\n    // borders of second square\n    final int sq2Start = size / 4;\n    final int sq2End = size * 3 / 4;\n\n    // draw inner square\n    for (int i = sq2Start; i &lt;= sq2End; i++) {\n        for (int j = sq2Start; j &lt;= sq2End; j++) {\n            if (i == sq2Start || i == sq2End || j == sq2Start || j == sq2End) {\n                buffer[i][j] = '*';\n            }\n        }\n    }\n\n    for (int i = 0; i &lt; size; i ++) {\n        for (int j = 0; j &lt; size; j ++) {\n            System.out.print(buffer[i][j]);\n        }\n        System.out.println();\n    }\n<\/code><\/pre>\n\n<p>Hope it would be helpful<\/p>\n",
        "answer_id": 18479049,
        "question_id": 18478428
    }],
    "answer_comments": {"18479049": [{
        "owner": {
            "profile_image": "https://www.gravatar.com/avatar/8a34f7c38326993309709d682cea2d64?s=256&d=identicon&r=PG&f=y&so-version=2",
            "account_id": 3218561,
            "user_type": "registered",
            "user_id": 2716525,
            "link": "https://stackoverflow.com/users/2716525/edu-shin",
            "reputation": 51,
            "display_name": "edu_shin"
        },
        "content_license": "CC BY-SA 3.0",
        "score": 0,
        "post_id": 18479049,
        "edited": false,
        "creation_date": 1377704850,
        "comment_id": 27186132
    }]}
}