{
    "question": {
        "owner": {
            "profile_image": "https://www.gravatar.com/avatar/bc32e812691c4ae99bb1fcfc0b8a0cdc?s=256&d=identicon&r=PG&f=y&so-version=2",
            "account_id": 3293396,
            "user_type": "registered",
            "user_id": 2771169,
            "link": "https://stackoverflow.com/users/2771169/jack-daniel",
            "reputation": 2621,
            "display_name": "Jack Daniel",
            "accept_rate": 56
        },
        "content_license": "CC BY-SA 3.0",
        "link": "https://stackoverflow.com/questions/35620706/java-runnable-jar-executing-very-huge-time-how-to-reduce-it",
        "last_activity_date": 1664795383,
        "creation_date": 1456384487,
        "answer_count": 2,
        "title": "Java - Runnable jar executing very huge time, How to reduce it?",
        "body": "<p>I am facing a strange problem. I have a project which is taking 3 to 4 minutes to execute while running through eclipse. But, the same project, taking 3 hours to complete the same task while extracting it as a runnable jar and running.<\/p>\n\n<p>I have tried increasing heap size by running trough command line -Xmx=3600m and -Xms=1200m parameters.<\/p>\n\n<p>Am I going in the right way. Is there any other ways to get down the execution time of runnable jar.<\/p>\n",
        "question_id": 35620706,
        "tags": [
            "java",
            "command-line",
            "jar",
            "heap-size"
        ],
        "score": 0,
        "is_answered": false,
        "view_count": 1989
    },
    "question_comments": [
        {
            "owner": {
                "profile_image": "https://i.sstatic.net/ZLnu7Pgm.png?s=256",
                "account_id": 2702906,
                "user_type": "registered",
                "user_id": 2333222,
                "link": "https://stackoverflow.com/users/2333222/suboptimal",
                "reputation": 23083,
                "display_name": "SubOptimal"
            },
            "content_license": "CC BY-SA 3.0",
            "score": 0,
            "post_id": 35620706,
            "edited": false,
            "creation_date": 1456394520,
            "comment_id": 58929945
        },
        {
            "owner": {
                "profile_image": "https://www.gravatar.com/avatar/bc32e812691c4ae99bb1fcfc0b8a0cdc?s=256&d=identicon&r=PG&f=y&so-version=2",
                "account_id": 3293396,
                "user_type": "registered",
                "user_id": 2771169,
                "link": "https://stackoverflow.com/users/2771169/jack-daniel",
                "reputation": 2621,
                "display_name": "Jack Daniel",
                "accept_rate": 56
            },
            "content_license": "CC BY-SA 3.0",
            "score": 0,
            "post_id": 35620706,
            "reply_to_user": {
                "profile_image": "https://i.sstatic.net/ZLnu7Pgm.png?s=256",
                "account_id": 2702906,
                "user_type": "registered",
                "user_id": 2333222,
                "link": "https://stackoverflow.com/users/2333222/suboptimal",
                "reputation": 23083,
                "display_name": "SubOptimal"
            },
            "edited": false,
            "creation_date": 1456386052,
            "comment_id": 58924568
        },
        {
            "owner": {
                "profile_image": "https://i.sstatic.net/ZLnu7Pgm.png?s=256",
                "account_id": 2702906,
                "user_type": "registered",
                "user_id": 2333222,
                "link": "https://stackoverflow.com/users/2333222/suboptimal",
                "reputation": 23083,
                "display_name": "SubOptimal"
            },
            "content_license": "CC BY-SA 3.0",
            "score": 0,
            "post_id": 35620706,
            "edited": false,
            "creation_date": 1456385808,
            "comment_id": 58924451
        },
        {
            "owner": {
                "profile_image": "https://www.gravatar.com/avatar/bc32e812691c4ae99bb1fcfc0b8a0cdc?s=256&d=identicon&r=PG&f=y&so-version=2",
                "account_id": 3293396,
                "user_type": "registered",
                "user_id": 2771169,
                "link": "https://stackoverflow.com/users/2771169/jack-daniel",
                "reputation": 2621,
                "display_name": "Jack Daniel",
                "accept_rate": 56
            },
            "content_license": "CC BY-SA 3.0",
            "score": 0,
            "post_id": 35620706,
            "reply_to_user": {
                "profile_image": "https://i.sstatic.net/ZLnu7Pgm.png?s=256",
                "account_id": 2702906,
                "user_type": "registered",
                "user_id": 2333222,
                "link": "https://stackoverflow.com/users/2333222/suboptimal",
                "reputation": 23083,
                "display_name": "SubOptimal"
            },
            "edited": false,
            "creation_date": 1456384850,
            "comment_id": 58923976
        },
        {
            "owner": {
                "profile_image": "https://i.sstatic.net/ZLnu7Pgm.png?s=256",
                "account_id": 2702906,
                "user_type": "registered",
                "user_id": 2333222,
                "link": "https://stackoverflow.com/users/2333222/suboptimal",
                "reputation": 23083,
                "display_name": "SubOptimal"
            },
            "content_license": "CC BY-SA 3.0",
            "score": 0,
            "post_id": 35620706,
            "edited": false,
            "creation_date": 1456384767,
            "comment_id": 58923940
        }
    ],
    "answers": [
        {
            "owner": {
                "profile_image": "https://i.sstatic.net/fRu7i.jpg?s=256",
                "account_id": 7878481,
                "user_type": "registered",
                "user_id": 5953463,
                "link": "https://stackoverflow.com/users/5953463/johngalt",
                "reputation": 61,
                "display_name": "JohnGalt"
            },
            "content_license": "CC BY-SA 3.0",
            "score": 0,
            "is_accepted": false,
            "last_activity_date": 1456384944,
            "creation_date": 1456384944,
            "body": "<p>It might be worth comparing java client versions and ensuring that the machine running the jar is using the 64-bit architecture java client if available. Your eclipse runs using the JDK files (often 64-bit), but many systems only run 32-bit java clients for compatibility (specifically with browsers).<\/p>\n\n<p>Is it possible that the jar file does not have all the libraries? Sometimes in my java programs, when an error is encountered, the process time increases significantly as the stack trace winds and unwinds. This is made worse if the error does not get handled properly. <\/p>\n\n<p>Missing libraries could also cause this, as could running the jar in a different environment as the environment from whence you are running eclipse. Directory separators (if using files), or different ASCII characters getting brought in from APIs and such for different OS types.<\/p>\n\n<p>Those are the causes I have noticed for unexpected java delays. Good luck!<\/p>\n",
            "answer_id": 35620835,
            "question_id": 35620706
        },
        {
            "owner": {
                "profile_image": "https://i.sstatic.net/beIr4.jpg?s=256",
                "account_id": 3723758,
                "user_type": "registered",
                "user_id": 3600553,
                "link": "https://stackoverflow.com/users/3600553/du-lacoste",
                "reputation": 13039,
                "display_name": "Du-Lacoste",
                "accept_rate": 71
            },
            "content_license": "CC BY-SA 4.0",
            "score": 0,
            "is_accepted": false,
            "last_activity_date": 1664795383,
            "creation_date": 1664795383,
            "body": "<p>Install Eclipse IDE and try Exporting as a Runnable Jar choosing following selection:<\/p>\n<p><strong>Option: Extract required libraries into generated jar<\/strong><\/p>\n<ul>\n<li><p>This way will extract only the actual class files from the libraries\nthat your application uses and includes in the runnable <code>jar<\/code> file.\nAs a result your Jar file will include your application class files\nas well as class files of all the libraries used by your application.<\/p>\n<\/li>\n<li><p>This method makes runnable jar perform just like it is run in your\n<code>eclipse<\/code> IDE.<\/p>\n<\/li>\n<li><p>Using this way I was able to run jar application without any lag and\ncompleted just as I run in <code>eclipse<\/code> IDE.<\/p>\n<\/li>\n<\/ul>\n",
            "answer_id": 73934564,
            "question_id": 35620706
        }
    ],
    "answer_comments": {"35620835": [
        {
            "owner": {
                "profile_image": "https://www.gravatar.com/avatar/bc32e812691c4ae99bb1fcfc0b8a0cdc?s=256&d=identicon&r=PG&f=y&so-version=2",
                "account_id": 3293396,
                "user_type": "registered",
                "user_id": 2771169,
                "link": "https://stackoverflow.com/users/2771169/jack-daniel",
                "reputation": 2621,
                "display_name": "Jack Daniel",
                "accept_rate": 56
            },
            "content_license": "CC BY-SA 3.0",
            "score": 0,
            "post_id": 35620835,
            "edited": false,
            "creation_date": 1456385869,
            "comment_id": 58924477
        },
        {
            "owner": {
                "profile_image": "https://i.sstatic.net/ZLnu7Pgm.png?s=256",
                "account_id": 2702906,
                "user_type": "registered",
                "user_id": 2333222,
                "link": "https://stackoverflow.com/users/2333222/suboptimal",
                "reputation": 23083,
                "display_name": "SubOptimal"
            },
            "content_license": "CC BY-SA 3.0",
            "score": 0,
            "post_id": 35620835,
            "edited": false,
            "creation_date": 1456385365,
            "comment_id": 58924263
        }
    ]}
}